json_translate/__init__.py
json_translate/__main__.py
json_translate/argparser.py
json_translate/commands.py
json_translate/datadiff.py
json_translate/files.py
json_translate/languages.py
json_translate/settings.py
json_translate/translators/__init__.py
json_translate/translators/aws.py
json_translate/translators/base.py
json_translate/translators/deepl.py
json_translate-0.4.4.dist-info/LICENSE.md
json_translate-0.4.4.dist-info/METADATA
json_translate-0.4.4.dist-info/WHEEL
json_translate-0.4.4.dist-info/entry_points.txt
json_translate-0.4.4.dist-info/top_level.txt
json_translate-0.4.4.dist-info/RECORD
