Metadata-Version: 2.1
Name: json-translate
Version: 0.4.4
Summary: CLI tool to translate json files using different external services
Author: Saigesp
Author-email: saigesp@gmail.com
Classifier: Intended Audience :: Developers
Classifier: Operating System :: OS Independent
Classifier: Topic :: Software Development
Classifier: Development Status :: 3 - Alpha
Classifier: Environment :: Console
Classifier: Programming Language :: Python :: 3
Classifier: License :: OSI Approved :: GNU Library or Lesser General Public License (LGPL)
Requires-Python: >=3.10
License-File: LICENSE.md
Requires-Dist: python-dotenv ==0.19.0
Requires-Dist: mergedeep ==1.3.4
Requires-Dist: boto3 ==1.28.40
